name1/__init__.py
name1-0.0.3.dist-info/LICENCE
name1-0.0.3.dist-info/METADATA
name1-0.0.3.dist-info/WHEEL
name1-0.0.3.dist-info/top_level.txt
name1-0.0.3.dist-info/RECORD
